noglobal/__init__.py
noglobal-1.0.4.dist-info/LICENSE
noglobal-1.0.4.dist-info/METADATA
noglobal-1.0.4.dist-info/WHEEL
noglobal-1.0.4.dist-info/top_level.txt
noglobal-1.0.4.dist-info/RECORD
