Metadata-Version: 2.1
Name: noglobal
Version: 1.0.4
Summary: My python utility functions
Author-email: Tatsuhiko Nakamine <bilzard@example.com>
Project-URL: Homepage, https://github.com/bilzard/noglobal
Project-URL: Bug Tracker, https://github.com/bilzard/noglobal/issues
Classifier: Programming Language :: Python :: 3
Classifier: License :: OSI Approved :: MIT License
Classifier: Operating System :: OS Independent
Requires-Python: >=3.7
License-File: LICENSE
